prune_envs/__init__.py
prune_envs/app.py
prune_envs/app.tcss
prune_envs/conda.py
prune_envs-1.1.0.dist-info/LICENSE
prune_envs-1.1.0.dist-info/METADATA
prune_envs-1.1.0.dist-info/WHEEL
prune_envs-1.1.0.dist-info/entry_points.txt
prune_envs-1.1.0.dist-info/RECORD
