Metadata-Version: 2.1
Name: prune-envs
Version: 1.1.0
Summary: Prune (conda) Environments
Home-page: https://github.com/davidfokkema/prune-envs
License: GPL-3.0-or-later
Author: David Fokkema
Author-email: davidfokkema@icloud.com
Requires-Python: >=3.10,<4.0
Classifier: Development Status :: 5 - Production/Stable
Classifier: Environment :: Console
Classifier: License :: OSI Approved :: GNU General Public License v3 or later (GPLv3+)
Classifier: Operating System :: MacOS
Classifier: Operating System :: Microsoft :: Windows
Classifier: Operating System :: POSIX
Classifier: Programming Language :: Python :: 3
Classifier: Programming Language :: Python :: 3.10
Classifier: Programming Language :: Python :: 3.11
Classifier: Programming Language :: Python :: 3.12
Classifier: Programming Language :: Python :: 3.13
Requires-Dist: textual (>=1.0.0,<2.0.0)
